brik/__init__.py
brik-0.0.1.dist-info/METADATA
brik-0.0.1.dist-info/WHEEL
brik-0.0.1.dist-info/top_level.txt
brik-0.0.1.dist-info/RECORD
