Metadata-Version: 2.4
Name: brik
Version: 0.0.1
Summary: Dummy lock package for brik
Author: AutoPublisher
